tagout/__init__.py
tagout/_document.py
tagout/_utils.py
tagout-1.0.0.dist-info/LICENSE
tagout-1.0.0.dist-info/METADATA
tagout-1.0.0.dist-info/WHEEL
tagout-1.0.0.dist-info/top_level.txt
tagout-1.0.0.dist-info/RECORD
