Metadata-Version: 2.1
Name: tagout
Version: 1.0.0
Summary: A small, pythonic, HTML/XML writer
Home-page: https://github.com/gesslerpd/tagout
Author: gesslerpd
Author-email: gesslerpd@users.noreply.github.com
License: MIT
Keywords: tags tag html xml generator writer stream
Platform: UNKNOWN
Classifier: Development Status :: 4 - Beta
Classifier: Intended Audience :: Developers
Classifier: License :: OSI Approved :: MIT License
Classifier: Programming Language :: Python :: 3
Classifier: Programming Language :: Python :: 3.6
Classifier: Programming Language :: Python :: 3.7
Classifier: Programming Language :: Python :: 3.8
